{
  "id": 8,
  "code": "RUT",
  "name": "Rute",
  "abbrev": "Rt",
  "chapters": [
    {
      "number": 1,
      "verses": [
        {
          "number": 1,
          "text": "No tempo em que os juízes governavam Israel, houve uma grande fome naquele país. Um homem chamado Elimeleque, que era de Belém, cidade de Judá, foi viver durante algum tempo em Moabe com a sua mulher e os seus dois filhos."
        },
        {
          "number": 2,
          "text": "A sua mulher se chamava Noemi e os seus filhos, Malom e Quiliom. Eles eram efrateus de Belém e, por causa da fome, foram para o país de Moabe e ali ficaram."
        },
        {
          "number": 3,
          "text": "Passado algum tempo, Elimeleque, o marido de Noemi, morreu e Noemi ficou sozinha com os seus dois filhos."
        },
        {
          "number": 4,
          "text": "Eles se casaram com mulheres moabitas: uma se chamava Orfa e a outra, Rute. Dez anos depois,"
        },
        {
          "number": 5,
          "text": "Malom e Quiliom também morreram e Noemi ficou sozinha, sem marido e sem filhos."
        },
        {
          "number": 6,
          "text": "Um dia Noemi soube que o SENHOR tinha abençoado ao seu povo com boas colheitas e resolveu sair de Moabe, com as suas duas noras,"
        },
        {
          "number": 7,
          "text": "e regressar a Judá. Por isso, Noemi e as noras deixaram o lugar onde tinham vivido juntas e partiram para Judá."
        },
        {
          "number": 8,
          "text": "No caminho, porém, Noemi disse às suas noras: — É melhor que cada uma de vocês volte para a casa da sua mãe. Vocês têm sido muito boas para comigo e para com os meus falecidos filhos. Que o SENHOR também seja bom com vocês e as abençoe!"
        },
        {
          "number": 9,
          "text": "Que o SENHOR permita que se casem e que cada uma viva em paz nos seus lares! Então Noemi beijou as suas duas noras e se despediu delas, mas elas começaram a chorar"
        },
        {
          "number": 10,
          "text": "e lhe disseram: — Nós queremos ir com a senhora para junto do seu povo."
        },
        {
          "number": 11,
          "text": "Noemi lhes disse: — Minhas filhas, voltem para as suas casas. Porque querem ir comigo? Não tenho mais filhos com quem vocês possam se casar."
        },
        {
          "number": 12,
          "text": "Vão, minhas filhas, voltem. Já não tenho filhos e sou velha demais para me casar outra vez. E mesmo que me casasse e ficasse grávida hoje à noite,"
        },
        {
          "number": 13,
          "text": "certamente vocês não iriam esperar até eles crescerem e se tornarem homens. Não seria possível para vocês ficarem tanto tempo sem se casar. Voltem, minhas filhas, a vida é pior para mim do que para vocês, porque o SENHOR está contra mim."
        },
        {
          "number": 14,
          "text": "As noras começaram a chorar de novo. Orfa, então, beijou a sua sogra e se despediu dela, mas Rute ficou com ela."
        },
        {
          "number": 15,
          "text": "Noemi, então, lhe disse: — A sua cunhada voltou para o seu povo e para adorar os seus deuses. Volte você também."
        },
        {
          "number": 16,
          "text": "Mas Rute lhe disse: — Não me obrigue a deixá-la e ficar longe da senhora! Para aonde a senhora for, eu também irei; onde a senhora viver, eu também viverei. O seu povo será o meu povo, o seu Deus será o meu Deus."
        },
        {
          "number": 17,
          "text": "Onde a senhora morrer, eu também morrerei e aí serei enterrada. Que o SENHOR me castigue duramente se eu não cumprir esta promessa: nada, a não ser a morte, poderá nos separar!"
        },
        {
          "number": 18,
          "text": "Quando Noemi viu que Rute estava decidida a ir com ela, deixou de insistir."
        },
        {
          "number": 19,
          "text": "Assim as duas continuaram a viagem até Belém. Chegando lá, toda a população ficou agitada. Todos falavam delas e as mulheres perguntavam: — Não é esta Noemi?"
        },
        {
          "number": 20,
          "text": "Mas ela dizia: — Não me chamem mais de Noemi. A partir de agora devem me chamar de Mara, porque o Deus Todo-Poderoso me fez muito infeliz."
        },
        {
          "number": 21,
          "text": "Quando saí daqui, tinha muito, mas agora o SENHOR me fez regressar sem nada. Por isso não me chamem Noemi, porque o SENHOR Todo-Poderoso me fez sofrer muito."
        },
        {
          "number": 22,
          "text": "Foi assim que Noemi regressou com a sua nora Rute, a moabita, de Moabe. Elas chegaram a Belém quando a colheita da cevada estava prestes a começar."
        }
      ]
    },
    {
      "number": 2,
      "verses": [
        {
          "number": 1,
          "text": "Havia um homem rico e importante que vivia em Belém, o seu nome era Boaz. Como era parente de Elimeleque, ele era um dos responsáveis por Noemi."
        },
        {
          "number": 2,
          "text": "Um dia, Rute, a moabita, disse a Noemi: — Deixe-me ir ao campo para ver se acho alguma pessoa boa que me permita apanhar as espigas que os trabalhadores costumam deixar cair. Noemi lhe disse: — Está bem, minha filha, vá."
        },
        {
          "number": 3,
          "text": "Rute foi então para o campo e ia atrás dos trabalhadores. Ela começou a apanhar as espigas que os trabalhadores deixavam cair e, por acaso, aquela parte do campo pertencia a Boaz, um parente de Elimeleque."
        },
        {
          "number": 4,
          "text": "Pouco tempo depois, Boaz chegou de Belém e cumprimentou os seus trabalhadores, dizendo: — Que o SENHOR esteja com vocês! E eles responderam: — Que o SENHOR abençoe você!"
        },
        {
          "number": 5,
          "text": "Depois Boaz perguntou ao encarregado dos seus trabalhadores: — Quem é aquela jovem?"
        },
        {
          "number": 6,
          "text": "E ele respondeu: — É a jovem moabita, que veio com Noemi."
        },
        {
          "number": 7,
          "text": "Ela me pediu que a deixasse andar atrás dos trabalhadores para apanhar as espigas que eles deixassem cair. Chegou aqui de manhã cedo e até agora não parou de trabalhar. Ela só descansou um pouco na sombra."
        },
        {
          "number": 8,
          "text": "Então Boaz disse a Rute: — Ouça, minha filha, não precisa ir trabalhar em outro campo. Fique com as outras mulheres que trabalham para mim."
        },
        {
          "number": 9,
          "text": "Vá aonde elas forem apanhar espigas. Eu vou dar ordem aos meus trabalhadores para não incomodarem você. Quando você tiver sede, pode beber da água dos potes que os meus trabalhadores encheram."
        },
        {
          "number": 10,
          "text": "Rute inclinou-se respeitosamente e disse a Boaz: — Por que é que o senhor me trata assim tão bem, a mim, que sou uma estrangeira?"
        },
        {
          "number": 11,
          "text": "Boaz lhe respondeu: — É que me contaram todo o bem que você fez pela sua sogra depois que o seu marido morreu. Me contaram como você deixou a sua família e o seu país para vir morar com ela aqui, com um povo que você não conhecia."
        },
        {
          "number": 12,
          "text": "Que o SENHOR recompense você pelo que tem feito! Que o SENHOR, o Deus de Israel, a abençoe ricamente por ter procurado proteção debaixo das suas asas."
        },
        {
          "number": 13,
          "text": "Ela disse: — O senhor foi muito bom comigo ao me receber muito bem, e eu nem sequer sou uma das suas trabalhadoras."
        },
        {
          "number": 14,
          "text": "Na hora do almoço, Boaz disse a Rute: — Venha comer conosco aqui. Molhe o seu pão no molho de vinagre. Então ela sentou-se com os trabalhadores e Boaz lhe deu grão de trigo torrado. Ela comeu até ficar satisfeita e ainda sobrou comida."
        },
        {
          "number": 15,
          "text": "Depois do almoço ela se levantou e continuou apanhando espigas. Enquanto isso, Boaz disse aos seus trabalhadores: — Deixem que ela apanhe espigas, até as que estão entre os feixes, e não a repreendam!"
        },
        {
          "number": 16,
          "text": "Também deixem cair espigas de propósito para que ela as possa apanhar, e não lhe façam mal!"
        },
        {
          "number": 17,
          "text": "Rute esteve apanhando espigas no campo até o fim da tarde. Depois retirou os grãos das espigas e os colocou num saco. Os grãos chegaram a pesar mais de vinte quilos."
        },
        {
          "number": 18,
          "text": "Depois ela regressou com os grãos à cidade. Ao chegar em casa, Rute mostrou para Noemi o que tinha apanhado e lhe deu o que tinha sobrado do seu almoço."
        },
        {
          "number": 19,
          "text": "Noemi lhe perguntou: — Onde você esteve trabalhando hoje para apanhar tantas espigas? Que seja abençoado o homem que se importou com você! Então Rute contou para Noemi o que Boaz tinha feito para ajudá-la. Ela disse: — O homem com quem trabalhei hoje chama-se Boaz."
        },
        {
          "number": 20,
          "text": "Noemi disse para Rute: — Que o SENHOR, que é bom para com os vivos e para com os mortos, o abençoe. Depois acrescentou: — Boaz é um dos nossos parentes mais próximos, e por isso ele é um dos responsáveis pela nossa proteção."
        },
        {
          "number": 21,
          "text": "Rute, a moabita, disse: — Ele também me disse para continuar trabalhando no seu campo com as suas trabalhadoras até o fim da colheita."
        },
        {
          "number": 22,
          "text": "Noemi disse para Rute: — Filha, é bom que siga trabalhando com elas. Alguém poderia lhe fazer mal se você for trabalhar em outros campos."
        },
        {
          "number": 23,
          "text": "Assim Rute ficou apanhando espigas com as mulheres até o fim da colheita da cevada e do trigo. No entanto, ela continuava morando com Noemi."
        }
      ]
    },
    {
      "number": 3,
      "verses": [
        {
          "number": 1,
          "text": "Certo dia, Noemi, a sogra de Rute, disse a ela: — Minha filha, tenho que achar um bom lar para você."
        },
        {
          "number": 2,
          "text": "Tenho estado pensando em Boaz. Ele é um dos nossos parentes e você já o conhece porque tem estado trabalhando com as suas trabalhadoras. Esta noite ele vai estar trabalhando no lugar onde se retira o grão das espigas de cevada."
        },
        {
          "number": 3,
          "text": "Faça isto: tome um bom banho, coloque perfume, vista-se com o seu melhor vestido e vá a esse lugar. Não deixe que Boaz a veja até ele ter comido e bebido."
        },
        {
          "number": 4,
          "text": "Depois observe bem o lugar onde ele vai se deitar. Quando ele estiver dormindo, aproxime-se dele, levante a manta dele e deite-se aos seus pés. Então ele lhe dirá o que você deve fazer."
        },
        {
          "number": 5,
          "text": "Rute disse: — Vou fazer o que diz."
        },
        {
          "number": 6,
          "text": "Ela desceu até o lugar onde se retira o grão das espigas e fez tudo o que a sua sogra tinha lhe dito."
        },
        {
          "number": 7,
          "text": "Boaz comeu, bebeu e ficou satisfeito. Então se deitou ao lado de um monte de cevada. E Rute chegou silenciosamente, levantou a manta que cobria os pés dele e deitou-se."
        },
        {
          "number": 8,
          "text": "No meio da noite, Boaz acordou assustado e procurou fugir, mas viu que a pessoa deitada ao seu lado era uma mulher."
        },
        {
          "number": 9,
          "text": "Então Boaz lhe perguntou: — Quem é você? Ela disse: — Sou Rute, a sua serva. Proteja-me debaixo das suas asas, pois o senhor é o protetor da nossa família."
        },
        {
          "number": 10,
          "text": "Ele lhe respondeu: — O SENHOR a abençoe, minha filha. Esta sua boa ação é mais nobre do que a sua primeira, porque veio falar comigo em vez de procurar por algum jovem, pobre ou rico."
        },
        {
          "number": 11,
          "text": "Agora, minha filha, não tenha medo. Vou fazer tudo o que me pediu, porque todos sabem que você é uma mulher de boas qualidades."
        },
        {
          "number": 12,
          "text": "Realmente eu sou um dos parentes que tem a obrigação de protegê-la e casar-se com você, mas há outro parente que tem mais direito do que eu."
        },
        {
          "number": 13,
          "text": "Fique aqui esta noite. Amanhã, se o outro parente quiser ser responsável por você, tudo bem, que o seja. Porém, se ele não quiser, prometo diante do SENHOR que eu tomarei conta de você. Fique aqui até o amanhecer."
        },
        {
          "number": 14,
          "text": "E ela ficou ali com ele até quase amanhecer, mas levantou-se antes disso para que ninguém a visse. Boaz pensou: “Ninguém deve saber que ela esteve neste lugar”."
        },
        {
          "number": 15,
          "text": "E disse a Rute: — Traga aqui o seu manto e segure-o. Ela segurou o manto, e ele colocou vinte quilos de cevada no manto e a ajudou a pôr o manto no ombro. Depois ela voltou para a cidade."
        },
        {
          "number": 16,
          "text": "Quando Rute chegou na casa da sua sogra, ela lhe perguntou: — Como foi, minha filha? Então Rute contou-lhe tudo o que Boaz tinha feito por ela."
        },
        {
          "number": 17,
          "text": "E lhe disse: — Ele também me deu estes vinte quilos de cevada e me disse que era para eu não voltar de mãos vazias para a casa da senhora, minha sogra."
        },
        {
          "number": 18,
          "text": "Noemi disse: — Fique aqui até saber o que irá acontecer. Boaz não vai descansar hoje, até que tudo fique resolvido."
        }
      ]
    },
    {
      "number": 4,
      "verses": [
        {
          "number": 1,
          "text": "Boaz foi à porta da cidade e sentou-se. Nesse momento, passou por ali o tal parente que ele tinha mencionado a Rute. Então Boaz o chamou: — Amigo, venha aqui e sente-se. E ele foi e sentou-se."
        },
        {
          "number": 2,
          "text": "Boaz também chamou dez líderes da cidade e lhes disse: — Sentem-se. E eles se sentaram."
        },
        {
          "number": 3,
          "text": "Boaz disse ao outro parente: — Noemi, a mulher que voltou de Moabe, está disposta a vender o terreno que pertenceu ao nosso parente Elimeleque."
        },
        {
          "number": 4,
          "text": "Quero lhe informar disso diante dos líderes do povo, que estão sentados aqui, para ver se deseja comprar o terreno. Você é o parente mais próximo e tem esse direito. Se quiser comprá-lo, então, compre-o. Se não quiser, diga-me, pois, depois de você, eu sou o parente mais próximo. Então o outro parente disse: — Eu comprarei o terreno."
        },
        {
          "number": 5,
          "text": "E Boaz lhe disse: — Quando você comprar o terreno de Noemi, também terá que se casar com Rute, a moabita, mulher do falecido Malom, para que o seu nome e a sua herança sejam restaurados."
        },
        {
          "number": 6,
          "text": "Ao ouvir isto, o parente disse: — Nesse caso, não posso usar o meu direito de comprar o terreno. Isso seria a ruína da minha herança. Compre você o terreno, eu não posso comprá-lo."
        },
        {
          "number": 7,
          "text": "(Naquele tempo, para confirmar um negócio, era costume em Israel uma das duas pessoas tirar uma das suas sandálias e dá-la ao outro.)"
        },
        {
          "number": 8,
          "text": "Quando o parente disse a Boaz: “Compre você o terreno”, ele tirou uma sandália do pé e a deu a Boaz."
        },
        {
          "number": 9,
          "text": "Boaz disse então aos líderes do povo e a todo o povo presente: — Vocês são testemunhas hoje de que compro de Noemi tudo o que pertenceu a Elimeleque e aos seus filhos Quiliom e Malom."
        },
        {
          "number": 10,
          "text": "Também recebo por esposa a moabita Rute, viúva de Malom. Recebo-a por esposa para que o nome de Malom se mantenha na herança e, ao mesmo tempo, seu nome não desapareça nem da família nem do seu povo. Disto vocês são testemunhas!"
        },
        {
          "number": 11,
          "text": "Então os líderes e todos os que ali estavam disseram: — Sim, somos testemunhas. Que o SENHOR faça com que essa mulher, que hoje entra em sua casa, seja como Raquel e Lia, que são as mães do povo de Israel. Que seja poderoso em Efrata e que o seu nome seja famoso em Belém!"
        },
        {
          "number": 12,
          "text": "Que os filhos que o SENHOR lhe der dessa jovem sejam tantos como os filhos da família de Perez, filho de Tamar e Judá."
        },
        {
          "number": 13,
          "text": "Assim Boaz tomou Rute por esposa e dormiu com ela. O SENHOR a abençoou, e ela ficou grávida e teve um filho."
        },
        {
          "number": 14,
          "text": "Então as mulheres da cidade disseram a Noemi: — Louvado seja o SENHOR que lhe deu um neto. Que o seu nome seja famoso em Israel."
        },
        {
          "number": 15,
          "text": "Ele cuidará de você na sua velhice, porque foi a sua nora, que ama você, a que lhe deu o neto. Ela é melhor para você do que sete filhos."
        },
        {
          "number": 16,
          "text": "Então Noemi pegou o menino no colo e cuidou dele."
        },
        {
          "number": 17,
          "text": "As vizinhas lhe deram o nome de Obede, dizendo: — Agora Noemi tem um filho. Obede foi o pai de Jessé e avô de Davi."
        },
        {
          "number": 18,
          "text": "Este é o registro da família de Perez: Perez foi o pai de Esrom"
        },
        {
          "number": 19,
          "text": "e Esrom foi o pai de Rame. Rame foi o pai de Aminadabe"
        },
        {
          "number": 20,
          "text": "e Aminadabe foi o pai de Naassom. Naassom foi o pai de Salmom"
        },
        {
          "number": 21,
          "text": "e Salmom foi o pai de Boaz. Boaz foi o pai de Obede"
        },
        {
          "number": 22,
          "text": "e Obede foi o pai de Jessé. Jessé foi o pai de Davi."
        }
      ]
    }
  ]
}